kal_middleware/__init__.py
kal_middleware/firebaseApi.py
kal_middleware/jwt.py
kal_middleware/kal_middleware.py
kal_middleware/keycloakAuth.py
kal_middleware/keycloakConfig.py
kal_middleware/keycloakSchemas.py
kal_middleware/sts.py
kal_middleware-2.0.5.7.dist-info/LICENSE
kal_middleware-2.0.5.7.dist-info/METADATA
kal_middleware-2.0.5.7.dist-info/WHEEL
kal_middleware-2.0.5.7.dist-info/entry_points.txt
kal_middleware-2.0.5.7.dist-info/top_level.txt
kal_middleware-2.0.5.7.dist-info/RECORD
