Metadata-Version: 2.2
Name: kal-middleware
Version: 2.0.5.7
Summary: Kaleidoo middleware package
Author-email: Bar Lander <barh@kaleidoo.ai>
License: MIT License
Project-URL: Homepage, https://github.com/BarLanderK/kal-middleware
Keywords: kal-middleware
Classifier: Intended Audience :: Developers
Classifier: License :: OSI Approved :: MIT License
Classifier: Natural Language :: English
Classifier: Programming Language :: Python :: 3.8
Classifier: Programming Language :: Python :: 3.9
Classifier: Programming Language :: Python :: 3.10
Classifier: Programming Language :: Python :: 3.11
Classifier: Programming Language :: Python :: 3.12
Requires-Python: >=3.8
License-File: LICENSE
Requires-Dist: firebase_admin
Requires-Dist: fastapi
Requires-Dist: google-auth
Requires-Dist: python-dotenv
Requires-Dist: kal-utils
Requires-Dist: python-jose
Requires-Dist: annotated-types==0.6.0
Requires-Dist: anyio==4.3.0
Requires-Dist: certifi==2024.2.2
Requires-Dist: cffi==1.16.0
Requires-Dist: charset-normalizer==3.3.2
Requires-Dist: click==8.1.7
Requires-Dist: colorama==0.4.6
Requires-Dist: cryptography==42.0.5
Requires-Dist: deprecation==2.1.0
Requires-Dist: h11==0.14.0
Requires-Dist: idna==3.6
Requires-Dist: jwcrypto==1.5.6
Requires-Dist: packaging==23.2
Requires-Dist: pycparser==2.21
Requires-Dist: pydantic
Requires-Dist: pydantic_core
Requires-Dist: python-dotenv
Requires-Dist: python-keycloak==3.9.1
Requires-Dist: requests==2.32.3
Requires-Dist: requests-toolbelt==1.0.0
Requires-Dist: sniffio==1.3.1
Requires-Dist: starlette
Requires-Dist: typing_extensions
Requires-Dist: urllib3==2.2.1
Requires-Dist: uvicorn
Requires-Dist: PyJWT==2.6.0
Provides-Extra: all
Requires-Dist: kal-middleware[extra]; extra == "all"
Provides-Extra: extra
Requires-Dist: pandas; extra == "extra"
